Metadata-Version: 1.1
Name: FullContact.py
Version: 0.0.3
Summary: Simple Python interface for FullContact, using Requests
Home-page: https://github.com/garbados/fullcontact.py
Author: ['Max Thayer', 'Amer Almadani', 'Brendan Maione-Downing']
Author-email: ['garbados@gmail.com', 'mad_dev@linuxmail.org', 'b.maionedowning@gmail.com']
License: MIT
Platform: any
Classifier: Environment :: Web Environment
Classifier: Intended Audience :: Developers
Classifier: Operating System :: OS Independent
Classifier: Programming Language :: Python
Classifier: Programming Language :: Python :: 2.7
Classifier: Programming Language :: Python :: 3.4
Classifier: Topic :: Internet :: WWW/HTTP :: Dynamic Content
Classifier: Topic :: Software Development :: Libraries :: Python Modules
